MANIFEST.in
README.md
setup.py
upgrade_requirements.py
upgrade_requirements.egg-info/PKG-INFO
upgrade_requirements.egg-info/SOURCES.txt
upgrade_requirements.egg-info/dependency_links.txt
upgrade_requirements.egg-info/entry_points.txt
upgrade_requirements.egg-info/top_level.txt