Metadata-Version: 1.0
Name: upgrade-requirements
Version: 1.4.0
Summary: Upgrade all your outdated requirements in a single command.
Home-page: http://github.com/joeyespo/upgrade-requirements.py
Author: Joe Esposito
Author-email: joe@joeyespo.com
License: MIT
Platform: any
